kahi_works/Kahi_works.py
kahi_works/__init__.py
kahi_works/_version.py
Kahi_works-0.0.4a0.dist-info/LICENSE
Kahi_works-0.0.4a0.dist-info/METADATA
Kahi_works-0.0.4a0.dist-info/WHEEL
Kahi_works-0.0.4a0.dist-info/top_level.txt
Kahi_works-0.0.4a0.dist-info/RECORD
