Metadata-Version: 2.1
Name: Kahi-works
Version: 0.0.4a0
Summary: Kahi plugin to insert and update works from all databases available
Home-page: https://github.com/colav/Kahi_plugins
Author: Colav
Author-email: colav@udea.edu.co
License: BSD
License-File: LICENSE
Requires-Dist: kahi
Requires-Dist: pymongo
Requires-Dist: pandas
Requires-Dist: thefuzz
Requires-Dist: joblib
Requires-Dist: langid
Requires-Dist: lingua-language-detector
Requires-Dist: pycld2
Requires-Dist: langdetect
Requires-Dist: fasttext-langdetect
Requires-Dist: iso639
